pure_energie/__init__.py
pure_energie/exceptions.py
pure_energie/models.py
pure_energie/pure_energie.py
pure_energie/py.typed
pure_energie-0.3.0.dist-info/LICENSE
pure_energie-0.3.0.dist-info/WHEEL
pure_energie-0.3.0.dist-info/METADATA
pure_energie-0.3.0.dist-info/RECORD
