Metadata-Version: 2.1
Name: pure-energie
Version: 0.3.0
Summary: Asynchronous Python client for the Pure Energie Meter devices
Home-page: https://github.com/klaasnicolaas/python-pem
License: MIT
Keywords: pure,energy,device,power,energy,async,client
Author: Klaas Schoute
Author-email: hello@student-techlife.com
Maintainer: Klaas Schoute
Maintainer-email: hello@student-techlife.com
Requires-Python: >=3.8,<4.0
Classifier: Framework :: AsyncIO
Classifier: Intended Audience :: Developers
Classifier: License :: OSI Approved :: MIT License
Classifier: Natural Language :: English
Classifier: Programming Language :: Python :: 3
Classifier: Programming Language :: Python :: 3.10
Classifier: Programming Language :: Python :: 3.8
Classifier: Programming Language :: Python :: 3.9
Classifier: Topic :: Software Development :: Libraries :: Python Modules
Requires-Dist: aiohttp (>=3.0.0)
Requires-Dist: yarl (>=1.6.0)
Project-URL: Bug Tracker, https://github.com/klaasnicolaas/python-pem/issues
Project-URL: Changelog, https://github.com/klaasnicolaas/python-pem/releases
Project-URL: Documentation, https://github.com/klaasnicolaas/python-pem
Project-URL: Repository, https://github.com/klaasnicolaas/python-pem
